<?xml version="1.0" encoding="utf-8" ?> 

<NEKTAR> 

<GEOMETRY DIM="1" SPACE="2"> 

	 <VERTEX> 
		 <V ID="0"> 0.000    0.0    0.0 </V> 
		 <V ID="1"> 5.812    0.0    0.0 </V> 

		 <V ID="2"> 5.812    -16.0    0.0 </V> 
		 <V ID="3"> 8.117    -16.0    0.0 </V> 

		 <V ID="4"> 5.812    5.0    0.0 </V> 
		 <V ID="5"> 9.721    5.0    0.0 </V> 

		 <V ID="6"> 9.721    3.0    0.0 </V> 
		 <V ID="7"> 13.629    3.0    0.0 </V> 

		 <V ID="8"> 9.721    8.4    0.0 </V> 
		 <V ID="9"> 20.543    8.4    0.0 </V> 

		 <V ID="10"> 13.629    1.5    0.0 </V> 
		 <V ID="11"> 30.765    1.5    0.0 </V> 

		 <V ID="12"> 13.629    4.5    0.0 </V> 
		 <V ID="13"> 62.232    4.5    0.0 </V> 

		 <V ID="14"> 62.232    3.5    0.0 </V> 
		 <V ID="15"> 89.289    3.5    0.0 </V> 

		 <V ID="16"> 62.232    6.0    0.0 </V> 
		 <V ID="17"> 69.948    6.0    0.0 </V> 

		 <V ID="18"> 69.948    5.0    0.0 </V> 
		 <V ID="19"> 79.067    5.0    0.0 </V> 

		 <V ID="20"> 69.948    8.0    0.0 </V> 
		 <V ID="21"> 89.690    8.0    0.0 </V> 

		 <V ID="22"> 20.543    6.5    0.0 </V> 
		 <V ID="23"> 41.087    6.5    0.0 </V> 

		 <V ID="24"> 20.543    12.0    0.0 </V> 
		 <V ID="25"> 39.283    12.0    0.0 </V> 

		 <V ID="26"> 8.117    -30.0    0.0 </V> 
		 <V ID="27"> 12.627    -30.0    0.0 </V> 

		 <V ID="28"> 8.117    -7.0    0.0 </V> 
		 <V ID="29"> 24.151    -7.0    0.0 </V> 

		 <V ID="30"> 24.151    -9.0    0.0 </V> 
		 <V ID="31"> 44.695    -9.0    0.0 </V> 

		 <V ID="32"> 24.151    -4.0    0.0 </V> 
		 <V ID="33"> 42.891    -4.0    0.0 </V> 

		 <V ID="34"> 12.627    -36.0    0.0 </V> 
		 <V ID="35"> 18.639    -36.0    0.0 </V> 

		 <V ID="36"> 12.627    -25.0    0.0 </V> 
		 <V ID="37"> 16.535    -25.0    0.0 </V> 

		 <V ID="38"> 16.535    -28.0    0.0 </V> 
		 <V ID="39"> 33.571    -28.0    0.0 </V> 

		 <V ID="40"> 16.535    -22.5    0.0 </V> 
		 <V ID="41"> 65.138    -22.5    0.0 </V> 

		 <V ID="42"> 65.138    -25.0    0.0 </V> 
		 <V ID="43"> 92.195    -25.0    0.0 </V> 

		 <V ID="44"> 65.138    -20.0    0.0 </V> 
		 <V ID="45"> 72.854    -20.0    0.0 </V> 

		 <V ID="46"> 72.854    -22.0    0.0 </V> 
		 <V ID="47"> 81.974    -22.0    0.0 </V> 

		 <V ID="48"> 72.854    -15.5    0.0 </V> 
		 <V ID="49"> 92.596    -15.5    0.0 </V> 

		 <V ID="50"> 18.639    -32.0    0.0 </V> 
		 <V ID="51"> 27.859    -32.0    0.0 </V> 

		 <V ID="52"> 18.639    -42.0    0.0 </V> 
		 <V ID="53"> 30.665    -42.0    0.0 </V> 

		 <V ID="54"> 30.665    -30.0    0.0 </V> 
		 <V ID="55"> 36.778    -30.0    0.0 </V> 

		 <V ID="56"> 30.665    -48.0    0.0 </V> 
		 <V ID="57"> 32.970    -48.0    0.0 </V> 

		 <V ID="58"> 32.970    -55.0    0.0 </V> 
		 <V ID="59"> 35.275    -55.0    0.0 </V> 

		 <V ID="60"> 32.970    -45.0    0.0 </V> 
		 <V ID="61"> 40.586    -45.0    0.0 </V> 

		 <V ID="62"> 35.275    -60.0    0.0 </V> 
		 <V ID="63"> 43.492    -60.0    0.0 </V> 

		 <V ID="64"> 35.275    -50.0    0.0 </V> 
		 <V ID="65"> 42.490    -50.0    0.0 </V> 

		 <V ID="66"> 36.778    -28.0    0.0 </V> 
		 <V ID="67"> 43.592    -28.0    0.0 </V> 

		 <V ID="68"> 36.778    -32.0    0.0 </V> 
		 <V ID="69"> 39.083    -32.0    0.0 </V> 

		 <V ID="70"> 39.083    -30.0    0.0 </V> 
		 <V ID="71"> 42.791    -30.0    0.0 </V> 

		 <V ID="72"> 39.083    -35.0    0.0 </V> 
		 <V ID="73"> 41.388    -35.0    0.0 </V> 

		 <V ID="74"> 41.388    -33.0    0.0 </V> 
		 <V ID="75"> 45.095    -33.0    0.0 </V> 

		 <V ID="76"> 41.388    -36.0    0.0 </V> 
		 <V ID="77"> 53.613    -36.0    0.0 </V> 

		 <V ID="78"> 53.613    -38.0    0.0 </V> 
		 <V ID="79"> 59.426    -38.0    0.0 </V> 

		 <V ID="80"> 53.613    -34.0    0.0 </V> 
		 <V ID="81"> 55.918    -34.0    0.0 </V> 

		 <V ID="82"> 55.918    -32.0    0.0 </V> 
		 <V ID="83"> 62.733    -32.0    0.0 </V> 

		 <V ID="84"> 55.918    -35.0    0.0 </V> 
		 <V ID="85"> 62.733    -35.0    0.0 </V> 

		 <V ID="86"> 62.733    -30.0    0.0 </V> 
		 <V ID="87"> 79.368    -30.0    0.0 </V> 

		 <V ID="88"> 62.733    -34.0    0.0 </V> 
		 <V ID="89"> 68.545    -34.0    0.0 </V> 

		 <V ID="90"> 79.368    -29.0    0.0 </V> 
		 <V ID="91"> 130.376    -29.0    0.0 </V> 

		 <V ID="92"> 79.368    -33.0    0.0 </V> 
		 <V ID="93"> 93.899    -33.0    0.0 </V> 

		 <V ID="94"> 130.376    -30.0    0.0 </V> 
		 <V ID="95"> 167.354    -30.0    0.0 </V> 

		 <V ID="96"> 130.376    -28.0    0.0 </V> 
		 <V ID="97"> 170.260    -28.0    0.0 </V> 

		 <V ID="98"> 62.733    -35.5    0.0 </V> 
		 <V ID="99"> 79.368    -35.5    0.0 </V> 

		 <V ID="100"> 62.733    -37.0    0.0 </V> 
		 <V ID="101"> 68.545    -37.0    0.0 </V> 

		 <V ID="102"> 79.368    -39.0    0.0 </V> 
		 <V ID="103"> 130.376    -39.0    0.0 </V> 

		 <V ID="104"> 79.368    -34.0    0.0 </V> 
		 <V ID="105"> 93.899    -34.0    0.0 </V> 

		 <V ID="106"> 130.376    -37.5    0.0 </V> 
		 <V ID="107"> 167.354    -37.5    0.0 </V> 

		 <V ID="108"> 130.376    -45.0    0.0 </V> 
		 <V ID="109"> 170.260    -45.0    0.0 </V> 
	 </VERTEX> 

	 <ELEMENT> 
		 <S ID="0"> 0 1 </S> 
		 <S ID="1"> 1 2 </S> 
		 <S ID="2"> 1 4 </S> 
		 <S ID="3"> 2 3 </S> 
		 <S ID="4"> 4 5 </S> 
		 <S ID="5"> 5 6 </S> 
		 <S ID="6"> 5 8 </S> 
		 <S ID="7"> 6 7 </S> 
		 <S ID="8"> 8 9 </S> 
		 <S ID="9"> 7 10 </S> 
		 <S ID="10"> 7 12 </S> 
		 <S ID="11"> 10 11 </S> 
		 <S ID="12"> 12 13 </S> 
		 <S ID="13"> 13 14 </S> 
		 <S ID="14"> 13 16 </S> 
		 <S ID="15"> 14 15 </S> 
		 <S ID="16"> 16 17 </S> 
		 <S ID="17"> 17 18 </S> 
		 <S ID="18"> 17 20 </S> 
		 <S ID="19"> 18 19 </S> 
		 <S ID="20"> 20 21 </S> 
		 <S ID="21"> 9 22 </S> 
		 <S ID="22"> 9 24 </S> 
		 <S ID="23"> 22 23 </S> 
		 <S ID="24"> 24 25 </S> 
		 <S ID="25"> 3 26 </S> 
		 <S ID="26"> 3 28 </S> 
		 <S ID="27"> 26 27 </S> 
		 <S ID="28"> 28 29 </S> 
		 <S ID="29"> 29 30 </S> 
		 <S ID="30"> 29 32 </S> 
		 <S ID="31"> 30 31 </S> 
		 <S ID="32"> 32 33 </S> 
		 <S ID="33"> 27 34 </S> 
		 <S ID="34"> 27 36 </S> 
		 <S ID="35"> 34 35 </S> 
		 <S ID="36"> 36 37 </S> 
		 <S ID="37"> 37 38 </S> 
		 <S ID="38"> 37 40 </S> 
		 <S ID="39"> 38 39 </S> 
		 <S ID="40"> 40 41 </S> 
		 <S ID="41"> 41 42 </S> 
		 <S ID="42"> 41 44 </S> 
		 <S ID="43"> 42 43 </S> 
		 <S ID="44"> 44 45 </S> 
		 <S ID="45"> 45 46 </S> 
		 <S ID="46"> 45 48 </S> 
		 <S ID="47"> 46 47 </S> 
		 <S ID="48"> 48 49 </S> 
		 <S ID="49"> 35 50 </S> 
		 <S ID="50"> 35 52 </S> 
		 <S ID="51"> 50 51 </S> 
		 <S ID="52"> 52 53 </S> 
		 <S ID="53"> 53 54 </S> 
		 <S ID="54"> 53 56 </S> 
		 <S ID="55"> 54 55 </S> 
		 <S ID="56"> 56 57 </S> 
		 <S ID="57"> 57 58 </S> 
		 <S ID="58"> 57 60 </S> 
		 <S ID="59"> 58 59 </S> 
		 <S ID="60"> 60 61 </S> 
		 <S ID="61"> 59 62 </S> 
		 <S ID="62"> 59 64 </S> 
		 <S ID="63"> 62 63 </S> 
		 <S ID="64"> 64 65 </S> 
		 <S ID="65"> 55 66 </S> 
		 <S ID="66"> 55 68 </S> 
		 <S ID="67"> 66 67 </S> 
		 <S ID="68"> 68 69 </S> 
		 <S ID="69"> 69 70 </S> 
		 <S ID="70"> 69 72 </S> 
		 <S ID="71"> 70 71 </S> 
		 <S ID="72"> 72 73 </S> 
		 <S ID="73"> 73 74 </S> 
		 <S ID="74"> 73 76 </S> 
		 <S ID="75"> 74 75 </S> 
		 <S ID="76"> 76 77 </S> 
		 <S ID="77"> 77 78 </S> 
		 <S ID="78"> 77 80 </S> 
		 <S ID="79"> 78 79 </S> 
		 <S ID="80"> 80 81 </S> 
		 <S ID="81"> 81 82 </S> 
		 <S ID="82"> 81 84 </S> 
		 <S ID="83"> 82 83 </S> 
		 <S ID="84"> 84 85 </S> 
		 <S ID="85"> 83 86 </S> 
		 <S ID="86"> 83 88 </S> 
		 <S ID="87"> 86 87 </S> 
		 <S ID="88"> 88 89 </S> 
		 <S ID="89"> 87 90 </S> 
		 <S ID="90"> 87 92 </S> 
		 <S ID="91"> 90 91 </S> 
		 <S ID="92"> 92 93 </S> 
		 <S ID="93"> 91 94 </S> 
		 <S ID="94"> 91 96 </S> 
		 <S ID="95"> 94 95 </S> 
		 <S ID="96"> 96 97 </S> 
		 <S ID="97"> 85 98 </S> 
		 <S ID="98"> 85 100 </S> 
		 <S ID="99"> 98 99 </S> 
		 <S ID="100"> 100 101 </S> 
		 <S ID="101"> 99 102 </S> 
		 <S ID="102"> 99 104 </S> 
		 <S ID="103"> 102 103 </S> 
		 <S ID="104"> 104 105 </S> 
		 <S ID="105"> 103 106 </S> 
		 <S ID="106"> 103 108 </S> 
		 <S ID="107"> 106 107 </S> 
		 <S ID="108"> 108 109 </S> 
	 </ELEMENT> 

	 <COMPOSITE> 
		 <C ID="0"> S[0] </C> 
		 <C ID="1"> V[0] </C> 
		 <C ID="2"> V[1] </C> 

		 <C ID="3"> S[1,3] </C> 
		 <C ID="4"> V[2] </C> 
		 <C ID="5"> V[3] </C> 

		 <C ID="6"> S[2,4] </C> 
		 <C ID="7"> V[4] </C> 
		 <C ID="8"> V[5] </C> 

		 <C ID="9"> S[5,7] </C> 
		 <C ID="10"> V[6] </C> 
		 <C ID="11"> V[7] </C> 

		 <C ID="12"> S[6,8] </C> 
		 <C ID="13"> V[8] </C> 
		 <C ID="14"> V[9] </C> 

		 <C ID="15"> S[9,11] </C> 
		 <C ID="16"> V[10] </C> 
		 <C ID="17"> V[11] </C> 

		 <C ID="18"> S[10,12] </C> 
		 <C ID="19"> V[12] </C> 
		 <C ID="20"> V[13] </C> 

		 <C ID="21"> S[13,15] </C> 
		 <C ID="22"> V[14] </C> 
		 <C ID="23"> V[15] </C> 

		 <C ID="24"> S[14,16] </C> 
		 <C ID="25"> V[16] </C> 
		 <C ID="26"> V[17] </C> 

		 <C ID="27"> S[17,19] </C> 
		 <C ID="28"> V[18] </C> 
		 <C ID="29"> V[19] </C> 

		 <C ID="30"> S[18,20] </C> 
		 <C ID="31"> V[20] </C> 
		 <C ID="32"> V[21] </C> 

		 <C ID="33"> S[21,23] </C> 
		 <C ID="34"> V[22] </C> 
		 <C ID="35"> V[23] </C> 

		 <C ID="36"> S[22,24] </C> 
		 <C ID="37"> V[24] </C> 
		 <C ID="38"> V[25] </C> 

		 <C ID="39"> S[25,27] </C> 
		 <C ID="40"> V[26] </C> 
		 <C ID="41"> V[27] </C> 

		 <C ID="42"> S[26,28] </C> 
		 <C ID="43"> V[28] </C> 
		 <C ID="44"> V[29] </C> 

		 <C ID="45"> S[29,31] </C> 
		 <C ID="46"> V[30] </C> 
		 <C ID="47"> V[31] </C> 

		 <C ID="48"> S[30,32] </C> 
		 <C ID="49"> V[32] </C> 
		 <C ID="50"> V[33] </C> 

		 <C ID="51"> S[33,35] </C> 
		 <C ID="52"> V[34] </C> 
		 <C ID="53"> V[35] </C> 

		 <C ID="54"> S[34,36] </C> 
		 <C ID="55"> V[36] </C> 
		 <C ID="56"> V[37] </C> 

		 <C ID="57"> S[37,39] </C> 
		 <C ID="58"> V[38] </C> 
		 <C ID="59"> V[39] </C> 

		 <C ID="60"> S[38,40] </C> 
		 <C ID="61"> V[40] </C> 
		 <C ID="62"> V[41] </C> 

		 <C ID="63"> S[41,43] </C> 
		 <C ID="64"> V[42] </C> 
		 <C ID="65"> V[43] </C> 

		 <C ID="66"> S[42,44] </C> 
		 <C ID="67"> V[44] </C> 
		 <C ID="68"> V[45] </C> 

		 <C ID="69"> S[45,47] </C> 
		 <C ID="70"> V[46] </C> 
		 <C ID="71"> V[47] </C> 

		 <C ID="72"> S[46,48] </C> 
		 <C ID="73"> V[48] </C> 
		 <C ID="74"> V[49] </C> 

		 <C ID="75"> S[49,51] </C> 
		 <C ID="76"> V[50] </C> 
		 <C ID="77"> V[51] </C> 

		 <C ID="78"> S[50,52] </C> 
		 <C ID="79"> V[52] </C> 
		 <C ID="80"> V[53] </C> 

		 <C ID="81"> S[53,55] </C> 
		 <C ID="82"> V[54] </C> 
		 <C ID="83"> V[55] </C> 

		 <C ID="84"> S[54,56] </C> 
		 <C ID="85"> V[56] </C> 
		 <C ID="86"> V[57] </C> 

		 <C ID="87"> S[57,59] </C> 
		 <C ID="88"> V[58] </C> 
		 <C ID="89"> V[59] </C> 

		 <C ID="90"> S[58,60] </C> 
		 <C ID="91"> V[60] </C> 
		 <C ID="92"> V[61] </C> 

		 <C ID="93"> S[61,63] </C> 
		 <C ID="94"> V[62] </C> 
		 <C ID="95"> V[63] </C> 

		 <C ID="96"> S[62,64] </C> 
		 <C ID="97"> V[64] </C> 
		 <C ID="98"> V[65] </C> 

		 <C ID="99"> S[65,67] </C> 
		 <C ID="100"> V[66] </C> 
		 <C ID="101"> V[67] </C> 

		 <C ID="102"> S[66,68] </C> 
		 <C ID="103"> V[68] </C> 
		 <C ID="104"> V[69] </C> 

		 <C ID="105"> S[69,71] </C> 
		 <C ID="106"> V[70] </C> 
		 <C ID="107"> V[71] </C> 

		 <C ID="108"> S[70,72] </C> 
		 <C ID="109"> V[72] </C> 
		 <C ID="110"> V[73] </C> 

		 <C ID="111"> S[73,75] </C> 
		 <C ID="112"> V[74] </C> 
		 <C ID="113"> V[75] </C> 

		 <C ID="114"> S[74,76] </C> 
		 <C ID="115"> V[76] </C> 
		 <C ID="116"> V[77] </C> 

		 <C ID="117"> S[77,79] </C> 
		 <C ID="118"> V[78] </C> 
		 <C ID="119"> V[79] </C> 

		 <C ID="120"> S[78,80] </C> 
		 <C ID="121"> V[80] </C> 
		 <C ID="122"> V[81] </C> 

		 <C ID="123"> S[81,83] </C> 
		 <C ID="124"> V[82] </C> 
		 <C ID="125"> V[83] </C> 

		 <C ID="126"> S[82,84] </C> 
		 <C ID="127"> V[84] </C> 
		 <C ID="128"> V[85] </C> 

		 <C ID="129"> S[85,87] </C> 
		 <C ID="130"> V[86] </C> 
		 <C ID="131"> V[87] </C> 

		 <C ID="132"> S[86,88] </C> 
		 <C ID="133"> V[88] </C> 
		 <C ID="134"> V[89] </C> 

		 <C ID="135"> S[89,91] </C> 
		 <C ID="136"> V[90] </C> 
		 <C ID="137"> V[91] </C> 

		 <C ID="138"> S[90,92] </C> 
		 <C ID="139"> V[92] </C> 
		 <C ID="140"> V[93] </C> 

		 <C ID="141"> S[93,95] </C> 
		 <C ID="142"> V[94] </C> 
		 <C ID="143"> V[95] </C> 

		 <C ID="144"> S[94,96] </C> 
		 <C ID="145"> V[96] </C> 
		 <C ID="146"> V[97] </C> 

		 <C ID="147"> S[97,99] </C> 
		 <C ID="148"> V[98] </C> 
		 <C ID="149"> V[99] </C> 

		 <C ID="150"> S[98,100] </C> 
		 <C ID="151"> V[100] </C> 
		 <C ID="152"> V[101] </C> 

		 <C ID="153"> S[101,103] </C> 
		 <C ID="154"> V[102] </C> 
		 <C ID="155"> V[103] </C> 

		 <C ID="156"> S[102,104] </C> 
		 <C ID="157"> V[104] </C> 
		 <C ID="158"> V[105] </C> 

		 <C ID="159"> S[105,107] </C> 
		 <C ID="160"> V[106] </C> 
		 <C ID="161"> V[107] </C> 

		 <C ID="162"> S[106,108] </C> 
		 <C ID="163"> V[108] </C> 
		 <C ID="164"> V[109] </C> 
	 </COMPOSITE> 

	 <DOMAIN> 
		 <D ID="0">    C[0] </D> 
		 <D ID="1">    C[3] </D> 
		 <D ID="2">    C[6] </D> 
		 <D ID="3">    C[9] </D> 
		 <D ID="4">   C[12] </D> 
		 <D ID="5">   C[15] </D> 
		 <D ID="6">   C[18] </D> 
		 <D ID="7">   C[21] </D> 
		 <D ID="8">   C[24] </D> 
		 <D ID="9">   C[27] </D> 
		 <D ID="10">  C[30] </D> 
		 <D ID="11">  C[33] </D> 
		 <D ID="12">  C[36] </D> 
		 <D ID="13">  C[39] </D> 
		 <D ID="14">  C[42] </D> 
		 <D ID="15">  C[45] </D> 
		 <D ID="16">  C[48] </D> 
		 <D ID="17">  C[51] </D> 
		 <D ID="18">  C[54] </D> 
		 <D ID="19">  C[57] </D> 
		 <D ID="20">  C[60] </D> 
		 <D ID="21">  C[63] </D> 
		 <D ID="22">  C[66] </D> 
		 <D ID="23">  C[69] </D> 
		 <D ID="24">  C[72] </D> 
		 <D ID="25">  C[75] </D> 
		 <D ID="26">  C[78] </D> 
		 <D ID="27">  C[81] </D> 
		 <D ID="28">  C[84] </D> 
		 <D ID="29">  C[87] </D> 
		 <D ID="30">  C[90] </D> 
		 <D ID="31">  C[93] </D> 
		 <D ID="32">  C[96] </D> 
		 <D ID="33">  C[99] </D> 
		 <D ID="34"> C[102] </D> 
		 <D ID="35"> C[105] </D> 
		 <D ID="36"> C[108] </D> 
		 <D ID="37"> C[111] </D> 
		 <D ID="38"> C[114] </D> 
		 <D ID="39"> C[117] </D> 
		 <D ID="40"> C[120] </D> 
		 <D ID="41"> C[123] </D> 
		 <D ID="42"> C[126] </D> 
		 <D ID="43"> C[129] </D> 
		 <D ID="44"> C[132] </D> 
		 <D ID="45"> C[135] </D> 
		 <D ID="46"> C[138] </D> 
		 <D ID="47"> C[141] </D> 
		 <D ID="48"> C[144] </D> 
		 <D ID="49"> C[147] </D> 
		 <D ID="50"> C[150] </D> 
		 <D ID="51"> C[153] </D> 
		 <D ID="52"> C[156] </D> 
		 <D ID="53"> C[159] </D> 
		 <D ID="54"> C[162] </D> 
	 </DOMAIN> 

</GEOMETRY> 

<EXPANSIONS> 
	 <E COMPOSITE="C[0]"   NUMMODES="4" FIELDS="A, u" TYPE="MODIFIED" /> 
	 <E COMPOSITE="C[3]"   NUMMODES="4" FIELDS="A, u" TYPE="MODIFIED" /> 
	 <E COMPOSITE="C[6]"   NUMMODES="4" FIELDS="A, u" TYPE="MODIFIED" /> 
	 <E COMPOSITE="C[9]"   NUMMODES="4" FIELDS="A, u" TYPE="MODIFIED" /> 
	 <E COMPOSITE="C[12]"  NUMMODES="4" FIELDS="A, u" TYPE="MODIFIED" /> 
	 <E COMPOSITE="C[15]"  NUMMODES="4" FIELDS="A, u" TYPE="MODIFIED" /> 
	 <E COMPOSITE="C[18]"  NUMMODES="4" FIELDS="A, u" TYPE="MODIFIED" /> 
	 <E COMPOSITE="C[21]"  NUMMODES="4" FIELDS="A, u" TYPE="MODIFIED" /> 
	 <E COMPOSITE="C[24]"  NUMMODES="4" FIELDS="A, u" TYPE="MODIFIED" /> 
	 <E COMPOSITE="C[27]"  NUMMODES="4" FIELDS="A, u" TYPE="MODIFIED" /> 
	 <E COMPOSITE="C[30]"  NUMMODES="4" FIELDS="A, u" TYPE="MODIFIED" /> 
	 <E COMPOSITE="C[33]"  NUMMODES="4" FIELDS="A, u" TYPE="MODIFIED" /> 
	 <E COMPOSITE="C[36]"  NUMMODES="4" FIELDS="A, u" TYPE="MODIFIED" /> 
	 <E COMPOSITE="C[39]"  NUMMODES="4" FIELDS="A, u" TYPE="MODIFIED" /> 
	 <E COMPOSITE="C[42]"  NUMMODES="4" FIELDS="A, u" TYPE="MODIFIED" /> 
	 <E COMPOSITE="C[45]"  NUMMODES="4" FIELDS="A, u" TYPE="MODIFIED" /> 
	 <E COMPOSITE="C[48]"  NUMMODES="4" FIELDS="A, u" TYPE="MODIFIED" /> 
	 <E COMPOSITE="C[51]"  NUMMODES="4" FIELDS="A, u" TYPE="MODIFIED" /> 
	 <E COMPOSITE="C[54]"  NUMMODES="4" FIELDS="A, u" TYPE="MODIFIED" /> 
	 <E COMPOSITE="C[57]"  NUMMODES="4" FIELDS="A, u" TYPE="MODIFIED" /> 
	 <E COMPOSITE="C[60]"  NUMMODES="4" FIELDS="A, u" TYPE="MODIFIED" /> 
	 <E COMPOSITE="C[63]"  NUMMODES="4" FIELDS="A, u" TYPE="MODIFIED" /> 
	 <E COMPOSITE="C[66]"  NUMMODES="4" FIELDS="A, u" TYPE="MODIFIED" /> 
	 <E COMPOSITE="C[69]"  NUMMODES="4" FIELDS="A, u" TYPE="MODIFIED" /> 
	 <E COMPOSITE="C[72]"  NUMMODES="4" FIELDS="A, u" TYPE="MODIFIED" /> 
	 <E COMPOSITE="C[75]"  NUMMODES="4" FIELDS="A, u" TYPE="MODIFIED" /> 
	 <E COMPOSITE="C[78]"  NUMMODES="4" FIELDS="A, u" TYPE="MODIFIED" /> 
	 <E COMPOSITE="C[81]"  NUMMODES="4" FIELDS="A, u" TYPE="MODIFIED" /> 
	 <E COMPOSITE="C[84]"  NUMMODES="4" FIELDS="A, u" TYPE="MODIFIED" /> 
	 <E COMPOSITE="C[87]"  NUMMODES="4" FIELDS="A, u" TYPE="MODIFIED" /> 
	 <E COMPOSITE="C[90]"  NUMMODES="4" FIELDS="A, u" TYPE="MODIFIED" /> 
	 <E COMPOSITE="C[93]"  NUMMODES="4" FIELDS="A, u" TYPE="MODIFIED" /> 
	 <E COMPOSITE="C[96]"  NUMMODES="4" FIELDS="A, u" TYPE="MODIFIED" /> 
	 <E COMPOSITE="C[99]"  NUMMODES="4" FIELDS="A, u" TYPE="MODIFIED" /> 
	 <E COMPOSITE="C[102]" NUMMODES="4" FIELDS="A, u" TYPE="MODIFIED" /> 
	 <E COMPOSITE="C[105]" NUMMODES="4" FIELDS="A, u" TYPE="MODIFIED" /> 
	 <E COMPOSITE="C[108]" NUMMODES="4" FIELDS="A, u" TYPE="MODIFIED" /> 
	 <E COMPOSITE="C[111]" NUMMODES="4" FIELDS="A, u" TYPE="MODIFIED" /> 
	 <E COMPOSITE="C[114]" NUMMODES="4" FIELDS="A, u" TYPE="MODIFIED" /> 
	 <E COMPOSITE="C[117]" NUMMODES="4" FIELDS="A, u" TYPE="MODIFIED" /> 
	 <E COMPOSITE="C[120]" NUMMODES="4" FIELDS="A, u" TYPE="MODIFIED" /> 
	 <E COMPOSITE="C[123]" NUMMODES="4" FIELDS="A, u" TYPE="MODIFIED" /> 
	 <E COMPOSITE="C[126]" NUMMODES="4" FIELDS="A, u" TYPE="MODIFIED" /> 
	 <E COMPOSITE="C[129]" NUMMODES="4" FIELDS="A, u" TYPE="MODIFIED" /> 
	 <E COMPOSITE="C[132]" NUMMODES="4" FIELDS="A, u" TYPE="MODIFIED" /> 
	 <E COMPOSITE="C[135]" NUMMODES="4" FIELDS="A, u" TYPE="MODIFIED" /> 
	 <E COMPOSITE="C[138]" NUMMODES="4" FIELDS="A, u" TYPE="MODIFIED" /> 
	 <E COMPOSITE="C[141]" NUMMODES="4" FIELDS="A, u" TYPE="MODIFIED" /> 
	 <E COMPOSITE="C[144]" NUMMODES="4" FIELDS="A, u" TYPE="MODIFIED" /> 
	 <E COMPOSITE="C[147]" NUMMODES="4" FIELDS="A, u" TYPE="MODIFIED" /> 
	 <E COMPOSITE="C[150]" NUMMODES="4" FIELDS="A, u" TYPE="MODIFIED" /> 
	 <E COMPOSITE="C[153]" NUMMODES="4" FIELDS="A, u" TYPE="MODIFIED" /> 
	 <E COMPOSITE="C[156]" NUMMODES="4" FIELDS="A, u" TYPE="MODIFIED" /> 
	 <E COMPOSITE="C[159]" NUMMODES="4" FIELDS="A, u" TYPE="MODIFIED" /> 
	 <E COMPOSITE="C[162]" NUMMODES="4" FIELDS="A, u" TYPE="MODIFIED" /> 
</EXPANSIONS> 

<CONDITIONS> 

	 <PARAMETERS> 
		 <P> TimeStep = 1e-06 </P> 
		 <P> T = 0.759493670886076 </P> 
		 <P> FinTime = 3 </P> 
		 <P> NumSteps = FinTime / TimeStep </P> 
		 <P> IO_CheckSteps = NumSteps / 3000 </P> 
		 <P> IO_InfoSteps = 1000 </P> 
		 <P> omega = 2 * PI / T </P> 
		 <P> rho = 0.00106 </P> 
		 <P> neu = 0.5 </P> 
		 <P> pext = 99.96852756546319 </P> 
		 <P> pout = 13.556787199758581 </P> 

		 <!--P> Age = 70 </P>
		 <P> Sex = M </P>
		 <P> EDV = 69.14257518971661 </P>
		 <P> EF = 0.5762527114374582 </P>
		 <P> SV = 39.84359642884252 </P>
		 <P> LVET = 0.2292163408354788 </P>
		 <P> HR = 79 </P>
		 <P> CO = 3.147644117878559 </P>
		 <P> HF = 1 </P>
		 <P> a_elas = 2.090339263662597 </P>
		 <P> a_musc = 1.340214070040349 </P>
		 <P> D_elas = 1.381879512507821 </P>
		 <P> D_musc = 1.1169450256112676 </P>
		 <P> Phi_scale = 0.9381293426443148 </P>
		 <P> PExt = 0.9996852756546319 </P>
		 <P> R_scale = 1.4221697431156535 </P>
		 <P> C_scale = 1.0311749483854016 </P>
		 <P> R_HF = 1.3998216129652823 </P>
		 <P> C_HF = 0.7143767396773303 </P>
		 <P> POut_scale = 1.0170132933052198 </P-->
	 </PARAMETERS> 

	 <SOLVERINFO> 
		 <I PROPERTY="EQTYPE" VALUE="PulseWavePropagation" /> 
		 <I PROPERTY="Projection" VALUE="DisContinuous" /> 
		 <I PROPERTY="TimeIntegrationMethod" VALUE="RungeKutta2_ImprovedEuler" /> 
		 <I PROPERTY="UpwindTypePulse" VALUE="UpwindPulse" /> 
		 <I PROPERTY="PressureArea" VALUE="Empirical" /> 
		 <I PROPERTY="OutputExtraFields" VALUE="True" /> 
	 </SOLVERINFO> 

	 <VARIABLES> 
		 <V ID="0"> A </V> 
		 <V ID="1"> u </V> 
	 </VARIABLES> 

	 <BOUNDARYREGIONS> 
		 <B ID="0"> C[1] </B> 
		 <B ID="1"> C[17] </B> 
		 <B ID="2"> C[23] </B> 
		 <B ID="3"> C[29] </B> 
		 <B ID="4"> C[32] </B> 
		 <B ID="5"> C[35] </B> 
		 <B ID="6"> C[38] </B> 
		 <B ID="7"> C[47] </B> 
		 <B ID="8"> C[50] </B> 
		 <B ID="9"> C[59] </B> 
		 <B ID="10"> C[65] </B> 
		 <B ID="11"> C[71] </B> 
		 <B ID="12"> C[74] </B> 
		 <B ID="13"> C[77] </B> 
		 <B ID="14"> C[92] </B> 
		 <B ID="15"> C[95] </B> 
		 <B ID="16"> C[98] </B> 
		 <B ID="17"> C[101] </B> 
		 <B ID="18"> C[107] </B> 
		 <B ID="19"> C[113] </B> 
		 <B ID="20"> C[119] </B> 
		 <B ID="21"> C[134] </B> 
		 <B ID="22"> C[140] </B> 
		 <B ID="23"> C[143] </B> 
		 <B ID="24"> C[146] </B> 
		 <B ID="25"> C[152] </B> 
		 <B ID="26"> C[158] </B> 
		 <B ID="27"> C[161] </B> 
		 <B ID="28"> C[164] </B> 
	 </BOUNDARYREGIONS> 

	 <BOUNDARYCONDITIONS> 

		 <REGION REF="0">
			 <D VAR="A" USERDEFINEDTYPE="Q-inflow" VALUE="0.5 * 102.58229195179787 * cos(0 * PI * t / T) + 0.0 * sin(0 * PI * t / T) + 
                         0.004487520642697203 * cos(1  * PI * t / T) + -0.009557855869124705 * sin(1  * PI * t / T) +
                         59.693182847950055 * cos(2  * PI * t / T) + 75.53336483283778 * sin(2  * PI * t / T) + 
                         0.025950176483527307 * cos(3  * PI * t / T) + -0.006062863932506169 * sin(3  * PI * t / T) + 
                         -15.516267952844775 * cos(4  * PI * t / T) + 73.0448796191366 * sin(4  * PI * t / T) + 
                         0.024773934335301343 * cos(5  * PI * t / T) + 0.018965992689203254 * sin(5  * PI * t / T) + 
                         -39.84980906202048 * cos(6  * PI * t / T) + 22.290857974076605 * sin(6  * PI * t / T) + 
                         0.0024777418310251006 * cos(7  * PI * t / T) + 0.022775569494666376 * sin(7  * PI * t / T) + 
                         -17.906082954925193 * cos(8  * PI * t / T) + -2.8935092839570684 * sin(8  * PI * t / T) + 
                         -0.0010620403745433234 * cos(9  * PI * t / T) + 0.009765284834811391 * sin(9  * PI * t / T) + 
                         -7.143722136843849 * cos(10 * PI * t / T) + 1.7631227416214081 * sin(10 * PI * t / T) + 
                         0.005066374479936627 * cos(11 * PI * t / T) + 0.010263020733100687 * sin(11 * PI * t / T) + 
                         -11.464726999075694 * cos(12 * PI * t / T) + 1.473915007025501 * sin(12 * PI * t / T) + 
                         -0.002499238657966777 * cos(13 * PI * t / T) + 0.01362540675877691 * sin(13 * PI * t / T) + 
                         -7.618151650919823 * cos(14 * PI * t / T) + -4.140995437886189 * sin(14 * PI * t / T) + 
                         -0.006419947063935709 * cos(15 * PI * t / T) + 0.006077117003946878 * sin(15 * PI * t / T) + 
                         -2.2491134503986765 * cos(16 * PI * t / T) + -1.9045651561669523 * sin(16 * PI * t / T) + 
                         -0.00022830780443211887 * cos(17 * PI * t / T) + 0.005060895784246801 * sin(17 * PI * t / T) + 
                         -4.589313874168538 * cos(18 * PI * t / T) + -0.3100860370648406 * sin(18 * PI * t / T) + 
                         -0.004357893405984847 * cos(19 * PI * t / T) + 0.00977397910397663 * sin(19 * PI * t / T) + 
                         -3.6693633050716143 * cos(20 * PI * t / T) + -3.9134040127475336 * sin(20 * PI * t / T) + 
                         -0.009180234558927202 * cos(21 * PI * t / T) + 0.002628036772218221 * sin(21 * PI * t / T) + 
                         0.4539339523019275 * cos(22 * PI * t / T) + -2.517905734626189 * sin(22 * PI * t / T) + 
                         -0.0014990086282045678 * cos(23 * PI * t / T) + -0.00049306450928935 * sin(23 * PI * t / T) + 
                         -1.2786354845125707 * cos(24 * PI * t / T) + 0.16619885591507283 * sin(24 * PI * t / T) + 
                         -0.002193216924625846 * cos(25 * PI * t / T) + 0.0068506208353119455 * sin(25 * PI * t / T) + 
                         -2.443592050421568 * cos(26 * PI * t / T) + -2.6298536873495526 * sin(26 * PI * t / T) + 
                         -0.010303379922286592 * cos(27 * PI * t / T) + 0.0021087570632643327 * sin(27 * PI * t / T) + 
                         1.2219557699424288 * cos(28 * PI * t / T) + -2.9929737189831958 * sin(28 * PI * t / T) + 
                         -0.0037158264289634977 * cos(29 * PI * t / T) + -0.005765121946534957 * sin(29 * PI * t / T) + 
                         1.2325181119989492 * cos(30 * PI * t / T) + 0.3155128010639427 * sin(30 * PI * t / T) + 
                         0.0020320363382740755 * cos(31 * PI * t / T) + 0.000988093861592317 * sin(31 * PI * t / T) + 
                         -1.1933062106235215 * cos(32 * PI * t / T) + -0.4058224180867842 * sin(32 * PI * t / T) + 
                         -0.005424344996645125 * cos(33 * PI * t / T) + 0.002674093239444745 * sin(33 * PI * t / T) + 
                         0.4475351530727155 * cos(34 * PI * t / T) + -1.864797330447845 * sin(34 * PI * t / T) + 
                         -0.0038142280673069797 * cos(35 * PI * t / T) + -0.0048275060608209555 * sin(35 * PI * t / T) + 
                         1.314091930303228 * cos(36 * PI * t / T) + 0.08533025251443846 * sin(36 * PI * t / T) + 
                         0.0028567077837080047 * cos(37 * PI * t / T) + -0.0014651214460410658 * sin(37 * PI * t / T) + 
                         -0.5333902948158188 * cos(38 * PI * t / T) + 0.28746864036912245 * sin(38 * PI * t / T) + 
                         -0.0023355367381975725 * cos(39 * PI * t / T) + 0.0023723510934155405 * sin(39 * PI * t / T) + 
                         0.1134835973034445 * cos(40 * PI * t / T) + -1.1053750526482793 * sin(40 * PI * t / T) + 
                         -0.003083612440310309 * cos(41 * PI * t / T) + -0.004169973369749669 * sin(41 * PI * t / T) +   
                         1.1461724432299907 * cos(42 * PI * t / T) + 0.19234781026350375 * sin(42 * PI * t / T) + 
                         0.0040380933572205955 * cos(43 * PI * t / T) + -0.0023983779863013736 * sin(43 * PI * t / T) +   
                         -0.41673898400380327 * cos(44 * PI * t / T) + 0.8225006563775195 * sin(44 * PI * t / T) + 
                         0.0002010588935818236 * cos(45 * PI * t / T) + 0.00382437940518989 * sin(45 * PI * t / T) +   
                         -0.4694514171265709 * cos(46 * PI * t / T) + -0.6686047366973678 * sin(46 * PI * t / T) + 
                         -0.0037617753170863504 * cos(47 * PI * t / T) + -0.0014751025082196056 * sin(47 * PI * t / T) +   
                         0.7681289211978805 * cos(48 * PI * t / T) + -0.2056348275647496 * sin(48 * PI * t / T) + 
                         0.002281008611581853 * cos(49 * PI * t / T) + -0.00305803260414594 * sin(49 * PI * t / T) +   
                         -0.023035026371340948 * cos(50 * PI * t / T) + 0.7086959386888602 * sin(50 * PI * t / T) + 
                         0.0016920894642218937 * cos(51 * PI * t / T) + 0.002899791719869723 * sin(51 * PI * t / T) +   
                         -0.5073547016927619 * cos(52 * PI * t / T) + -0.2719287311938317 * sin(52 * PI * t / T) + 
                         -0.003001922580005952 * cos(53 * PI * t / T) + 1.1406929827680508e-05 * sin(53 * PI * t / T) +   
                         0.4740643399934166 * cos(54 * PI * t / T) + -0.24945440117907633 * sin(54 * PI * t / T) + 
                         0.0015794945006704585 * cos(55 * PI * t / T) + -0.0027662271814274404 * sin(55 * PI * t / T) +   
                         0.062437910947570244 * cos(56 * PI * t / T) + 0.6186194253868631 * sin(56 * PI * t / T) + 
                         0.002584617411074475 * cos(57 * PI * t / T) + 0.0027955264016567734 * sin(57 * PI * t / T) +   
                         -0.6168178542476886 * cos(58 * PI * t / T) + -0.06503821157202008 * sin(58 * PI * t / T) + 
                         -0.002985247600913545 * cos(59 * PI * t / T) + 0.0020280709514733336 * sin(59 * PI * t / T) +   
                         0.20308017629667663 * cos(60 * PI * t / T) + -0.48689075454183556 * sin(60 * PI * t / T) + 
                         -0.00037960180476508956 * cos(61 * PI * t / T) + -0.002831697807809898 * sin(61 * PI * t / T) +  
                         0.28257956776455867 * cos(62 * PI * t / T) + 0.34752988602550205 * sin(62 * PI * t / T) + 
                         0.003008262579350077 * cos(63 * PI * t / T) + 0.0010070267531608556 * sin(63 * PI * t / T) +  
                         -0.4643565918749573 * cos(64 * PI * t / T) + 0.16077410893737243 * sin(64 * PI * t / T) + 
                         -0.0014899962916047464 * cos(65 * PI * t / T) + 0.0028503295805262434 * sin(65 * PI * t / T) +  
                         -0.09127011697738048 * cos(66 * PI * t / T) + -0.4407973320499147 * sin(66 * PI * t / T) + 
                         -0.0018444652405578427 * cos(67 * PI * t / T) + -0.0018332048501791395 * sin(67 * PI * t / T) +  
                         0.31332367440654924 * cos(68 * PI * t / T) + 0.07286341513336488 * sin(68 * PI * t / T) + 
                         0.002301722223618785 * cos(69 * PI * t / T) + -0.0006670076571084295 * sin(69 * PI * t / T) +  
                         -0.24058218407082993 * cos(70 * PI * t / T) + 0.26566659289056066 * sin(70 * PI * t / T)"/> 
			 <D VAR="u" USERDEFINEDTYPE="Q-inflow" VALUE="1.0" /> 
		 </REGION> 

		 <REGION REF="1"> 
			 <D VAR="A" USERDEFINEDTYPE="RCR-terminal"  VALUE="89.78435586170775" /> 
			 <D VAR="u" USERDEFINEDTYPE="RCR-terminal"  VALUE="0.006644559526933813" /> 
		 </REGION> 

		 <REGION REF="2"> 
			 <D VAR="A" USERDEFINEDTYPE="RCR-terminal"  VALUE="78.83504417125559" /> 
			 <D VAR="u" USERDEFINEDTYPE="RCR-terminal"  VALUE="0.00727070981494864" /> 
		 </REGION> 

		 <REGION REF="3"> 
			 <D VAR="A" USERDEFINEDTYPE="RCR-terminal"  VALUE="1258.1754524301396" /> 
			 <D VAR="u" USERDEFINEDTYPE="RCR-terminal"  VALUE="0.002394104042409633" /> 
		 </REGION> 

		 <REGION REF="4"> 
			 <D VAR="A" USERDEFINEDTYPE="RCR-terminal"  VALUE="78.83504417125559" /> 
			 <D VAR="u" USERDEFINEDTYPE="RCR-terminal"  VALUE="0.005664818488040024" /> 
		 </REGION> 

		 <REGION REF="5"> 
			 <D VAR="A" USERDEFINEDTYPE="RCR-terminal"  VALUE="37.42673814190922" /> 
			 <D VAR="u" USERDEFINEDTYPE="RCR-terminal"  VALUE="0.019005502859744165" /> 
		 </REGION> 

		 <REGION REF="6"> 
			 <D VAR="A" USERDEFINEDTYPE="RCR-terminal"  VALUE="207.04153014673182" /> 
			 <D VAR="u" USERDEFINEDTYPE="RCR-terminal"  VALUE="0.014217294774924899" /> 
		 </REGION> 

		 <REGION REF="7"> 
			 <D VAR="A" USERDEFINEDTYPE="RCR-terminal"  VALUE="37.42673814190922" /> 
			 <D VAR="u" USERDEFINEDTYPE="RCR-terminal"  VALUE="0.013922635815859096" /> 
		 </REGION> 

		 <REGION REF="8"> 
			 <D VAR="A" USERDEFINEDTYPE="RCR-terminal"  VALUE="207.04153014673182" /> 
			 <D VAR="u" USERDEFINEDTYPE="RCR-terminal"  VALUE="0.012743999979595893" /> 
		 </REGION> 

		 <REGION REF="9"> 
			 <D VAR="A" USERDEFINEDTYPE="RCR-terminal"  VALUE="89.78435586170775" /> 
			 <D VAR="u" USERDEFINEDTYPE="RCR-terminal"  VALUE="0.006644559526933813" /> 
		 </REGION> 

		 <REGION REF="10"> 
			 <D VAR="A" USERDEFINEDTYPE="RCR-terminal"  VALUE="78.83504417125559" /> 
			 <D VAR="u" USERDEFINEDTYPE="RCR-terminal"  VALUE="0.006246769932194981" /> 
		 </REGION> 

		 <REGION REF="11"> 
			 <D VAR="A" USERDEFINEDTYPE="RCR-terminal"  VALUE="1258.1754524301396" /> 
			 <D VAR="u" USERDEFINEDTYPE="RCR-terminal"  VALUE="0.002040513291530672" /> 
		 </REGION> 

		 <REGION REF="12"> 
			 <D VAR="A" USERDEFINEDTYPE="RCR-terminal"  VALUE="78.83504417125559" /> 
			 <D VAR="u" USERDEFINEDTYPE="RCR-terminal"  VALUE="0.009576416169638531" /> 
		 </REGION> 

		 <REGION REF="13"> 
			 <D VAR="A" USERDEFINEDTYPE="RCR-terminal"  VALUE="119.44703662311451" /> 
			 <D VAR="u" USERDEFINEDTYPE="RCR-terminal"  VALUE="0.07661132935710825" /> 
		 </REGION> 

		 <REGION REF="14"> 
			 <D VAR="A" USERDEFINEDTYPE="RCR-terminal"  VALUE="54.14932326914525" /> 
			 <D VAR="u" USERDEFINEDTYPE="RCR-terminal"  VALUE="0.015101271652122302" /> 
		 </REGION> 

		 <REGION REF="15"> 
			 <D VAR="A" USERDEFINEDTYPE="RCR-terminal"  VALUE="80.82582811497416" /> 
			 <D VAR="u" USERDEFINEDTYPE="RCR-terminal"  VALUE="0.006047875134825566" /> 
		 </REGION> 

		 <REGION REF="16"> 
			 <D VAR="A" USERDEFINEDTYPE="RCR-terminal"  VALUE="34.639640620703204" /> 
			 <D VAR="u" USERDEFINEDTYPE="RCR-terminal"  VALUE="0.010313063567303035" /> 
		 </REGION> 

		 <REGION REF="17"> 
			 <D VAR="A" USERDEFINEDTYPE="RCR-terminal"  VALUE="13.895671927155655" /> 
			 <D VAR="u" USERDEFINEDTYPE="RCR-terminal"  VALUE="0.03543273982766257" /> 
		 </REGION> 

		 <REGION REF="18"> 
			 <D VAR="A" USERDEFINEDTYPE="RCR-terminal"  VALUE="16.881847842733517" /> 
			 <D VAR="u" USERDEFINEDTYPE="RCR-terminal"  VALUE="0.017016554886050007" /> 
		 </REGION> 

		 <REGION REF="19"> 
			 <D VAR="A" USERDEFINEDTYPE="RCR-terminal"  VALUE="16.881847842733517" /> 
			 <D VAR="u" USERDEFINEDTYPE="RCR-terminal"  VALUE="0.017016554886050007" /> 
		 </REGION> 

		 <REGION REF="20"> 
			 <D VAR="A" USERDEFINEDTYPE="RCR-terminal"  VALUE="102.72445149587848" /> 
			 <D VAR="u" USERDEFINEDTYPE="RCR-terminal"  VALUE="0.009797410388937883" /> 
		 </REGION> 

		 <REGION REF="21"> 
			 <D VAR="A" USERDEFINEDTYPE="RCR-terminal"  VALUE="118.65072304562709" /> 
			 <D VAR="u" USERDEFINEDTYPE="RCR-terminal"  VALUE="0.010092069348003684" /> 
		 </REGION> 

		 <REGION REF="22"> 
			 <D VAR="A" USERDEFINEDTYPE="RCR-terminal"  VALUE="71.27006518512499" /> 
			 <D VAR="u" USERDEFINEDTYPE="RCR-terminal"  VALUE="0.009355421950339182" /> 
		 </REGION> 

		 <REGION REF="23"> 
			 <D VAR="A" USERDEFINEDTYPE="RCR-terminal"  VALUE="211.02309803416898" /> 
			 <D VAR="u" USERDEFINEDTYPE="RCR-terminal"  VALUE="0.005473290164647254" /> 
		 </REGION> 

		 <REGION REF="24"> 
			 <D VAR="A" USERDEFINEDTYPE="RCR-terminal"  VALUE="211.02309803416898" /> 
			 <D VAR="u" USERDEFINEDTYPE="RCR-terminal"  VALUE="0.0037790011500188976" /> 
		 </REGION> 

		 <REGION REF="25"> 
			 <D VAR="A" USERDEFINEDTYPE="RCR-terminal"  VALUE="118.65072304562709" /> 
			 <D VAR="u" USERDEFINEDTYPE="RCR-terminal"  VALUE="0.010092069348003684" /> 
		 </REGION> 

		 <REGION REF="26"> 
			 <D VAR="A" USERDEFINEDTYPE="RCR-terminal"  VALUE="71.27006518512499" /> 
			 <D VAR="u" USERDEFINEDTYPE="RCR-terminal"  VALUE="0.009355421950339182" /> 
		 </REGION> 

		 <REGION REF="27"> 
			 <D VAR="A" USERDEFINEDTYPE="RCR-terminal"  VALUE="211.02309803416898" /> 
			 <D VAR="u" USERDEFINEDTYPE="RCR-terminal"  VALUE="0.005473290164647254" /> 
		 </REGION> 

		 <REGION REF="28"> 
			 <D VAR="A" USERDEFINEDTYPE="RCR-terminal"  VALUE="211.02309803416898" /> 
			 <D VAR="u" USERDEFINEDTYPE="RCR-terminal"  VALUE="0.0037790011500188976" /> 
		 </REGION> 

	 </BOUNDARYCONDITIONS> 

		<FUNCTION NAME="InitialConditions"> 
				<E VAR="A" DOMAIN="0"  VALUE="13.7694 * (1 - 0.00113376 * (x - 0))" /> 
				<E VAR="u" DOMAIN="0"  VALUE="0.0" /> 
				<E VAR="A" DOMAIN="1"  VALUE="9.9832 * (1 - 0.0362073 * (x - 5.8123))" /> 
				<E VAR="u" DOMAIN="1"  VALUE="0.0" /> 
				<E VAR="A" DOMAIN="2"  VALUE="6.48869 * (1 - 0.0534575 * (x - 5.8123))" /> 
				<E VAR="u" DOMAIN="2"  VALUE="0.0" /> 
				<E VAR="A" DOMAIN="3"  VALUE="2.08831 * (1 - 0.0979571 * (x - 9.72058))" /> 
				<E VAR="u" DOMAIN="3"  VALUE="0.0" /> 
				<E VAR="A" DOMAIN="4"  VALUE="1.91508 * (1 - 0.0675484 * (x - 9.72058))" /> 
				<E VAR="u" DOMAIN="4"  VALUE="0.0" /> 
				<E VAR="A" DOMAIN="5"  VALUE="0.217711 * (1 - 0.0250117 * (x - 13.6289))" /> 
				<E VAR="u" DOMAIN="5"  VALUE="0.0" /> 
				<E VAR="A" DOMAIN="6"  VALUE="1.04319 * (1 - 0.0136455 * (x - 13.6289))" /> 
				<E VAR="u" DOMAIN="6"  VALUE="0.0" /> 
				<E VAR="A" DOMAIN="7"  VALUE="0.217711 * (1 - 0.0110498 * (x - 62.2317))" /> 
				<E VAR="u" DOMAIN="7"  VALUE="0.0" /> 
				<E VAR="A" DOMAIN="8"  VALUE="0.217711 * (1 - 0.020231 * (x - 62.2317))" /> 
				<E VAR="u" DOMAIN="8"  VALUE="0.0" /> 
				<E VAR="A" DOMAIN="9"  VALUE="0.0699742 * (1 - 0.0292171 * (x - 69.9481))" /> 
				<E VAR="u" DOMAIN="9"  VALUE="0.0" /> 
				<E VAR="A" DOMAIN="10"  VALUE="0.162339 * (1 - 0.0118383 * (x - 69.9481))" /> 
				<E VAR="u" DOMAIN="10"  VALUE="0.0" /> 
				<E VAR="A" DOMAIN="11"  VALUE="0.516781 * (1 - 0.0210782 * (x - 20.5435))" /> 
				<E VAR="u" DOMAIN="11"  VALUE="0.0" /> 
				<E VAR="A" DOMAIN="12"  VALUE="0.0990596 * (1 - 0.034202 * (x - 20.5435))" /> 
				<E VAR="u" DOMAIN="12"  VALUE="0.0" /> 
				<E VAR="A" DOMAIN="13"  VALUE="7.25898 * (1 - 0.0119306 * (x - 8.11718))" /> 
				<E VAR="u" DOMAIN="13"  VALUE="0.0" /> 
				<E VAR="A" DOMAIN="14"  VALUE="1.49979 * (1 - 0.0466508 * (x - 8.11718))" /> 
				<E VAR="u" DOMAIN="14"  VALUE="0.0" /> 
				<E VAR="A" DOMAIN="15"  VALUE="0.294332 * (1 - 0.0194958 * (x - 24.1511))" /> 
				<E VAR="u" DOMAIN="15"  VALUE="0.0" /> 
				<E VAR="A" DOMAIN="16"  VALUE="0.0582053 * (1 - 0.0315331 * (x - 24.1511))" /> 
				<E VAR="u" DOMAIN="16"  VALUE="0.0" /> 
				<E VAR="A" DOMAIN="17"  VALUE="6.36451 * (1 - 0.0172875 * (x - 12.6267))" /> 
				<E VAR="u" DOMAIN="17"  VALUE="0.0" /> 
				<E VAR="A" DOMAIN="18"  VALUE="1.91508 * (1 - 0.105243 * (x - 12.6267))" /> 
				<E VAR="u" DOMAIN="18"  VALUE="0.0" /> 
				<E VAR="A" DOMAIN="19"  VALUE="0.217711 * (1 - 0.0251588 * (x - 16.535))" /> 
				<E VAR="u" DOMAIN="19"  VALUE="0.0" /> 
				<E VAR="A" DOMAIN="20"  VALUE="1.04319 * (1 - 0.0136455 * (x - 16.535))" /> 
				<E VAR="u" DOMAIN="20"  VALUE="0.0" /> 
				<E VAR="A" DOMAIN="21"  VALUE="0.194373 * (1 - 0.0133051 * (x - 65.1379))" /> 
				<E VAR="u" DOMAIN="21"  VALUE="0.0" /> 
				<E VAR="A" DOMAIN="22"  VALUE="0.294332 * (1 - 0 * (x - 65.1379))" /> 
				<E VAR="u" DOMAIN="22"  VALUE="0.0" /> 
				<E VAR="A" DOMAIN="23"  VALUE="0.0513303 * (1 - 0 * (x - 72.8542))" /> 
				<E VAR="u" DOMAIN="23"  VALUE="0.0" /> 
				<E VAR="A" DOMAIN="24"  VALUE="0.267088 * (1 - 0.00936457 * (x - 72.8542))" /> 
				<E VAR="u" DOMAIN="24"  VALUE="0.0" /> 
				<E VAR="A" DOMAIN="25"  VALUE="2.53464 * (1 - 0.0470776 * (x - 18.6395))" /> 
				<E VAR="u" DOMAIN="25"  VALUE="0.0" /> 
				<E VAR="A" DOMAIN="26"  VALUE="4.33439 * (1 - 0.0322586 * (x - 18.6395))" /> 
				<E VAR="u" DOMAIN="26"  VALUE="0.0" /> 
				<E VAR="A" DOMAIN="27"  VALUE="2.38107 * (1 - 0 * (x - 30.6649))" /> 
				<E VAR="u" DOMAIN="27"  VALUE="0.0" /> 
				<E VAR="A" DOMAIN="28"  VALUE="0.967078 * (1 - 0.0946766 * (x - 30.6649))" /> 
				<E VAR="u" DOMAIN="28"  VALUE="0.0" /> 
				<E VAR="A" DOMAIN="29"  VALUE="0.429277 * (1 - 0.0488227 * (x - 32.9698))" /> 
				<E VAR="u" DOMAIN="29"  VALUE="0.0" /> 
				<E VAR="A" DOMAIN="30"  VALUE="0.463639 * (1 - 0.0441413 * (x - 32.9698))" /> 
				<E VAR="u" DOMAIN="30"  VALUE="0.0" /> 
				<E VAR="A" DOMAIN="31"  VALUE="0.162339 * (1 - 0.0143458 * (x - 35.2747))" /> 
				<E VAR="u" DOMAIN="31"  VALUE="0.0" /> 
				<E VAR="A" DOMAIN="32"  VALUE="0.279897 * (1 - 0.0185809 * (x - 35.2747))" /> 
				<E VAR="u" DOMAIN="32"  VALUE="0.0" /> 
				<E VAR="A" DOMAIN="33"  VALUE="0.991314 * (1 - 0.0281094 * (x - 36.7779))" /> 
				<E VAR="u" DOMAIN="33"  VALUE="0.0" /> 
				<E VAR="A" DOMAIN="34"  VALUE="2.08831 * (1 - 0.0145826 * (x - 36.7779))" /> 
				<E VAR="u" DOMAIN="34"  VALUE="0.0" /> 
				<E VAR="A" DOMAIN="35"  VALUE="0.429277 * (1 - 0 * (x - 39.0827))" /> 
				<E VAR="u" DOMAIN="35"  VALUE="0.0" /> 
				<E VAR="A" DOMAIN="36"  VALUE="2.19584 * (1 - 0 * (x - 39.0827))" /> 
				<E VAR="u" DOMAIN="36"  VALUE="0.0" /> 
				<E VAR="A" DOMAIN="37"  VALUE="0.429277 * (1 - 0 * (x - 41.3876))" /> 
				<E VAR="u" DOMAIN="37"  VALUE="0.0" /> 
				<E VAR="A" DOMAIN="38"  VALUE="2.12385 * (1 - 0.00804017 * (x - 41.3876))" /> 
				<E VAR="u" DOMAIN="38"  VALUE="0.0" /> 
				<E VAR="A" DOMAIN="39"  VALUE="0.351335 * (1 - 0.093034 * (x - 53.6135))" /> 
				<E VAR="u" DOMAIN="39"  VALUE="0.0" /> 
				<E VAR="A" DOMAIN="40"  VALUE="1.84789 * (1 - 0.0307059 * (x - 53.6135))" /> 
				<E VAR="u" DOMAIN="40"  VALUE="0.0" /> 
				<E VAR="A" DOMAIN="41"  VALUE="0.647641 * (1 - 0.031653 * (x - 55.9184))" /> 
				<E VAR="u" DOMAIN="41"  VALUE="0.0" /> 
				<E VAR="A" DOMAIN="42"  VALUE="0.647641 * (1 - 0.031653 * (x - 55.9184))" /> 
				<E VAR="u" DOMAIN="42"  VALUE="0.0" /> 
				<E VAR="A" DOMAIN="43"  VALUE="0.425524 * (1 - 0.00552257 * (x - 62.7328))" /> 
				<E VAR="u" DOMAIN="43"  VALUE="0.0" /> 
				<E VAR="A" DOMAIN="44"  VALUE="0.166321 * (1 - 0 * (x - 62.7328))" /> 
				<E VAR="u" DOMAIN="44"  VALUE="0.0" /> 
				<E VAR="A" DOMAIN="45"  VALUE="0.280454 * (1 - 0.0091333 * (x - 79.368))" /> 
				<E VAR="u" DOMAIN="45"  VALUE="0.0" /> 
				<E VAR="A" DOMAIN="46"  VALUE="0.166321 * (1 - 0.00996672 * (x - 79.368))" /> 
				<E VAR="u" DOMAIN="46"  VALUE="0.0" /> 
				<E VAR="A" DOMAIN="47"  VALUE="0.0997091 * (1 - 0.0050006 * (x - 130.376))" /> 
				<E VAR="u" DOMAIN="47"  VALUE="0.0" /> 
				<E VAR="A" DOMAIN="48"  VALUE="0.0703758 * (1 - 0.00546487 * (x - 130.376))" /> 
				<E VAR="u" DOMAIN="48"  VALUE="0.0" /> 
				<E VAR="A" DOMAIN="49"  VALUE="0.425524 * (1 - 0.00552257 * (x - 62.7328))" /> 
				<E VAR="u" DOMAIN="49"  VALUE="0.0" /> 
				<E VAR="A" DOMAIN="50"  VALUE="0.166321 * (1 - 0 * (x - 62.7328))" /> 
				<E VAR="u" DOMAIN="50"  VALUE="0.0" /> 
				<E VAR="A" DOMAIN="51"  VALUE="0.280454 * (1 - 0.0091333 * (x - 79.368))" /> 
				<E VAR="u" DOMAIN="51"  VALUE="0.0" /> 
				<E VAR="A" DOMAIN="52"  VALUE="0.166321 * (1 - 0.00996672 * (x - 79.368))" /> 
				<E VAR="u" DOMAIN="52"  VALUE="0.0" /> 
				<E VAR="A" DOMAIN="53"  VALUE="0.0997091 * (1 - 0.0050006 * (x - 130.376))" /> 
				<E VAR="u" DOMAIN="53"  VALUE="0.0" /> 
				<E VAR="A" DOMAIN="54"  VALUE="0.0703758 * (1 - 0.00546487 * (x - 130.376))" /> 
				<E VAR="u" DOMAIN="54"  VALUE="0.0" /> 
		</FUNCTION> 

		<FUNCTION NAME="A_0"> 
				<E VAR="A_0" DOMAIN="0"  VALUE="13.7694 * (1 - 0.00113376 * (x - 0))" /> 
				<E VAR="A_0" DOMAIN="1"  VALUE="9.9832 * (1 - 0.0362073 * (x - 5.8123))" /> 
				<E VAR="A_0" DOMAIN="2"  VALUE="6.48869 * (1 - 0.0534575 * (x - 5.8123))" /> 
				<E VAR="A_0" DOMAIN="3"  VALUE="2.08831 * (1 - 0.0979571 * (x - 9.72058))" /> 
				<E VAR="A_0" DOMAIN="4"  VALUE="1.91508 * (1 - 0.0675484 * (x - 9.72058))" /> 
				<E VAR="A_0" DOMAIN="5"  VALUE="0.217711 * (1 - 0.0250117 * (x - 13.6289))" /> 
				<E VAR="A_0" DOMAIN="6"  VALUE="1.04319 * (1 - 0.0136455 * (x - 13.6289))" /> 
				<E VAR="A_0" DOMAIN="7"  VALUE="0.217711 * (1 - 0.0110498 * (x - 62.2317))" /> 
				<E VAR="A_0" DOMAIN="8"  VALUE="0.217711 * (1 - 0.020231 * (x - 62.2317))" /> 
				<E VAR="A_0" DOMAIN="9"  VALUE="0.0699742 * (1 - 0.0292171 * (x - 69.9481))" /> 
				<E VAR="A_0" DOMAIN="10"  VALUE="0.162339 * (1 - 0.0118383 * (x - 69.9481))" /> 
				<E VAR="A_0" DOMAIN="11"  VALUE="0.516781 * (1 - 0.0210782 * (x - 20.5435))" /> 
				<E VAR="A_0" DOMAIN="12"  VALUE="0.0990596 * (1 - 0.034202 * (x - 20.5435))" /> 
				<E VAR="A_0" DOMAIN="13"  VALUE="7.25898 * (1 - 0.0119306 * (x - 8.11718))" /> 
				<E VAR="A_0" DOMAIN="14"  VALUE="1.49979 * (1 - 0.0466508 * (x - 8.11718))" /> 
				<E VAR="A_0" DOMAIN="15"  VALUE="0.294332 * (1 - 0.0194958 * (x - 24.1511))" /> 
				<E VAR="A_0" DOMAIN="16"  VALUE="0.0582053 * (1 - 0.0315331 * (x - 24.1511))" /> 
				<E VAR="A_0" DOMAIN="17"  VALUE="6.36451 * (1 - 0.0172875 * (x - 12.6267))" /> 
				<E VAR="A_0" DOMAIN="18"  VALUE="1.91508 * (1 - 0.105243 * (x - 12.6267))" /> 
				<E VAR="A_0" DOMAIN="19"  VALUE="0.217711 * (1 - 0.0251588 * (x - 16.535))" /> 
				<E VAR="A_0" DOMAIN="20"  VALUE="1.04319 * (1 - 0.0136455 * (x - 16.535))" /> 
				<E VAR="A_0" DOMAIN="21"  VALUE="0.194373 * (1 - 0.0133051 * (x - 65.1379))" /> 
				<E VAR="A_0" DOMAIN="22"  VALUE="0.294332 * (1 - 0 * (x - 65.1379))" /> 
				<E VAR="A_0" DOMAIN="23"  VALUE="0.0513303 * (1 - 0 * (x - 72.8542))" /> 
				<E VAR="A_0" DOMAIN="24"  VALUE="0.267088 * (1 - 0.00936457 * (x - 72.8542))" /> 
				<E VAR="A_0" DOMAIN="25"  VALUE="2.53464 * (1 - 0.0470776 * (x - 18.6395))" /> 
				<E VAR="A_0" DOMAIN="26"  VALUE="4.33439 * (1 - 0.0322586 * (x - 18.6395))" /> 
				<E VAR="A_0" DOMAIN="27"  VALUE="2.38107 * (1 - 0 * (x - 30.6649))" /> 
				<E VAR="A_0" DOMAIN="28"  VALUE="0.967078 * (1 - 0.0946766 * (x - 30.6649))" /> 
				<E VAR="A_0" DOMAIN="29"  VALUE="0.429277 * (1 - 0.0488227 * (x - 32.9698))" /> 
				<E VAR="A_0" DOMAIN="30"  VALUE="0.463639 * (1 - 0.0441413 * (x - 32.9698))" /> 
				<E VAR="A_0" DOMAIN="31"  VALUE="0.162339 * (1 - 0.0143458 * (x - 35.2747))" /> 
				<E VAR="A_0" DOMAIN="32"  VALUE="0.279897 * (1 - 0.0185809 * (x - 35.2747))" /> 
				<E VAR="A_0" DOMAIN="33"  VALUE="0.991314 * (1 - 0.0281094 * (x - 36.7779))" /> 
				<E VAR="A_0" DOMAIN="34"  VALUE="2.08831 * (1 - 0.0145826 * (x - 36.7779))" /> 
				<E VAR="A_0" DOMAIN="35"  VALUE="0.429277 * (1 - 0 * (x - 39.0827))" /> 
				<E VAR="A_0" DOMAIN="36"  VALUE="2.19584 * (1 - 0 * (x - 39.0827))" /> 
				<E VAR="A_0" DOMAIN="37"  VALUE="0.429277 * (1 - 0 * (x - 41.3876))" /> 
				<E VAR="A_0" DOMAIN="38"  VALUE="2.12385 * (1 - 0.00804017 * (x - 41.3876))" /> 
				<E VAR="A_0" DOMAIN="39"  VALUE="0.351335 * (1 - 0.093034 * (x - 53.6135))" /> 
				<E VAR="A_0" DOMAIN="40"  VALUE="1.84789 * (1 - 0.0307059 * (x - 53.6135))" /> 
				<E VAR="A_0" DOMAIN="41"  VALUE="0.647641 * (1 - 0.031653 * (x - 55.9184))" /> 
				<E VAR="A_0" DOMAIN="42"  VALUE="0.647641 * (1 - 0.031653 * (x - 55.9184))" /> 
				<E VAR="A_0" DOMAIN="43"  VALUE="0.425524 * (1 - 0.00552257 * (x - 62.7328))" /> 
				<E VAR="A_0" DOMAIN="44"  VALUE="0.166321 * (1 - 0 * (x - 62.7328))" /> 
				<E VAR="A_0" DOMAIN="45"  VALUE="0.280454 * (1 - 0.0091333 * (x - 79.368))" /> 
				<E VAR="A_0" DOMAIN="46"  VALUE="0.166321 * (1 - 0.00996672 * (x - 79.368))" /> 
				<E VAR="A_0" DOMAIN="47"  VALUE="0.0997091 * (1 - 0.0050006 * (x - 130.376))" /> 
				<E VAR="A_0" DOMAIN="48"  VALUE="0.0703758 * (1 - 0.00546487 * (x - 130.376))" /> 
				<E VAR="A_0" DOMAIN="49"  VALUE="0.425524 * (1 - 0.00552257 * (x - 62.7328))" /> 
				<E VAR="A_0" DOMAIN="50"  VALUE="0.166321 * (1 - 0 * (x - 62.7328))" /> 
				<E VAR="A_0" DOMAIN="51"  VALUE="0.280454 * (1 - 0.0091333 * (x - 79.368))" /> 
				<E VAR="A_0" DOMAIN="52"  VALUE="0.166321 * (1 - 0.00996672 * (x - 79.368))" /> 
				<E VAR="A_0" DOMAIN="53"  VALUE="0.0997091 * (1 - 0.0050006 * (x - 130.376))" /> 
				<E VAR="A_0" DOMAIN="54"  VALUE="0.0703758 * (1 - 0.00546487 * (x - 130.376))" /> 
		</FUNCTION> 

		<FUNCTION NAME="MaterialProperties"> 
				<E VAR="beta" DOMAIN="0"  VALUE="543.045 * (1 + 0.000907609 * (x - 0))" /> 
				<E VAR="beta" DOMAIN="1"  VALUE="702.349 * (1 + 0.0292161 * (x - 5.8123))" /> 
				<E VAR="beta" DOMAIN="2"  VALUE="991.386 * (1 + 0.0437441 * (x - 5.8123))" /> 
				<E VAR="beta" DOMAIN="3"  VALUE="2455.46 * (1 + 0.0819547 * (x - 9.72058))" /> 
				<E VAR="beta" DOMAIN="4"  VALUE="2631.59 * (1 + 0.0600844 * (x - 9.72058))" /> 
				<E VAR="beta" DOMAIN="5"  VALUE="17833.7 * (1 + 0.0210624 * (x - 13.6289))" /> 
				<E VAR="beta" DOMAIN="6"  VALUE="5091.62 * (1 + 0.0119605 * (x - 13.6289))" /> 
				<E VAR="beta" DOMAIN="7"  VALUE="17833.7 * (1 + 0.00914223 * (x - 62.2317))" /> 
				<E VAR="beta" DOMAIN="8"  VALUE="17833.7 * (1 + 0.0164548 * (x - 62.2317))" /> 
				<E VAR="beta" DOMAIN="9"  VALUE="44217.6 * (1 + 0.0240746 * (x - 69.9481))" /> 
				<E VAR="beta" DOMAIN="10"  VALUE="22553.2 * (1 + 0.00971584 * (x - 69.9481))" /> 
				<E VAR="beta" DOMAIN="11"  VALUE="8931.01 * (1 + 0.0177614 * (x - 20.5435))" /> 
				<E VAR="beta" DOMAIN="12"  VALUE="33483.3 * (1 + 0.0298459 * (x - 20.5435))" /> 
				<E VAR="beta" DOMAIN="13"  VALUE="906.292 * (1 + 0.00959698 * (x - 8.11718))" /> 
				<E VAR="beta" DOMAIN="14"  VALUE="3199.96 * (1 + 0.0416622 * (x - 8.11718))" /> 
				<E VAR="beta" DOMAIN="15"  VALUE="14011.2 * (1 + 0.0163513 * (x - 24.1511))" /> 
				<E VAR="beta" DOMAIN="16"  VALUE="51236 * (1 + 0.0272601 * (x - 24.1511))" /> 
				<E VAR="beta" DOMAIN="17"  VALUE="1006.83 * (1 + 0.0139801 * (x - 12.6267))" /> 
				<E VAR="beta" DOMAIN="18"  VALUE="2631.59 * (1 + 0.088404 * (x - 12.6267))" /> 
				<E VAR="beta" DOMAIN="19"  VALUE="17833.7 * (1 + 0.0211863 * (x - 16.535))" /> 
				<E VAR="beta" DOMAIN="20"  VALUE="5091.62 * (1 + 0.0119605 * (x - 16.535))" /> 
				<E VAR="beta" DOMAIN="21"  VALUE="19527.1 * (1 + 0.0110968 * (x - 65.1379))" /> 
				<E VAR="beta" DOMAIN="22"  VALUE="14011.2 * (1 + 0 * (x - 65.1379))" /> 
				<E VAR="beta" DOMAIN="23"  VALUE="56656.1 * (1 + 0 * (x - 72.8542))" /> 
				<E VAR="beta" DOMAIN="24"  VALUE="15143.3 * (1 + 0.00764158 * (x - 72.8542))" /> 
				<E VAR="beta" DOMAIN="25"  VALUE="2102.98 * (1 + 0.0396757 * (x - 18.6395))" /> 
				<E VAR="beta" DOMAIN="26"  VALUE="1369.07 * (1 + 0.0270078 * (x - 18.6395))" /> 
				<E VAR="beta" DOMAIN="27"  VALUE="2210.81 * (1 + 0 * (x - 30.6649))" /> 
				<E VAR="beta" DOMAIN="28"  VALUE="4545.69 * (1 + 0.0775585 * (x - 30.6649))" /> 
				<E VAR="beta" DOMAIN="29"  VALUE="8705.19 * (1 + 0.0395188 * (x - 32.9698))" /> 
				<E VAR="beta" DOMAIN="30"  VALUE="9740.96 * (1 + 0.0366977 * (x - 32.9698))" /> 
				<E VAR="beta" DOMAIN="31"  VALUE="22553.2 * (1 + 0.0116188 * (x - 35.2747))" /> 
				<E VAR="beta" DOMAIN="32"  VALUE="14586.4 * (1 + 0.0150756 * (x - 35.2747))" /> 
				<E VAR="beta" DOMAIN="33"  VALUE="4456.56 * (1 + 0.0229552 * (x - 36.7779))" /> 
				<E VAR="beta" DOMAIN="34"  VALUE="2455.46 * (1 + 0.0117058 * (x - 36.7779))" /> 
				<E VAR="beta" DOMAIN="35"  VALUE="8705.19 * (1 + 0 * (x - 39.0827))" /> 
				<E VAR="beta" DOMAIN="36"  VALUE="2358.78 * (1 + 0 * (x - 39.0827))" /> 
				<E VAR="beta" DOMAIN="37"  VALUE="8705.19 * (1 + 0 * (x - 41.3876))" /> 
				<E VAR="beta" DOMAIN="38"  VALUE="2422.53 * (1 + 0.00649799 * (x - 41.3876))" /> 
				<E VAR="beta" DOMAIN="39"  VALUE="12161 * (1 + 0.0797285 * (x - 53.6135))" /> 
				<E VAR="beta" DOMAIN="40"  VALUE="2707.87 * (1 + 0.0247437 * (x - 53.6135))" /> 
				<E VAR="beta" DOMAIN="41"  VALUE="4080.27 * (1 + 0.0259222 * (x - 55.9184))" /> 
				<E VAR="beta" DOMAIN="42"  VALUE="4080.27 * (1 + 0.0259222 * (x - 55.9184))" /> 
				<E VAR="beta" DOMAIN="43"  VALUE="5709.75 * (1 + 0.00446021 * (x - 62.7328))" /> 
				<E VAR="beta" DOMAIN="44"  VALUE="14500.6 * (1 + 0 * (x - 62.7328))" /> 
				<E VAR="beta" DOMAIN="45"  VALUE="9546.73 * (1 + 0.00773401 * (x - 79.368))" /> 
				<E VAR="beta" DOMAIN="46"  VALUE="14500.6 * (1 + 0.00809612 * (x - 79.368))" /> 
				<E VAR="beta" DOMAIN="47"  VALUE="21835.1 * (1 + 0.00408056 * (x - 130.376))" /> 
				<E VAR="beta" DOMAIN="48"  VALUE="28853.9 * (1 + 0.00447666 * (x - 130.376))" /> 
				<E VAR="beta" DOMAIN="49"  VALUE="5709.75 * (1 + 0.00446021 * (x - 62.7328))" /> 
				<E VAR="beta" DOMAIN="50"  VALUE="14500.6 * (1 + 0 * (x - 62.7328))" /> 
				<E VAR="beta" DOMAIN="51"  VALUE="9546.73 * (1 + 0.00773401 * (x - 79.368))" /> 
				<E VAR="beta" DOMAIN="52"  VALUE="14500.6 * (1 + 0.00809612 * (x - 79.368))" /> 
				<E VAR="beta" DOMAIN="53"  VALUE="21835.1 * (1 + 0.00408056 * (x - 130.376))" /> 
				<E VAR="beta" DOMAIN="54"  VALUE="28853.9 * (1 + 0.00447666 * (x - 130.376))" /> 
		</FUNCTION> 

		<FUNCTION NAME="Viscoelasticity"> 
				<E VAR="gamma" DOMAIN="0"  VALUE="0.088372 * (1 + 0.000700162 * (x - 0))" /> 
				<E VAR="gamma" DOMAIN="1"  VALUE="0.10747 * (1 + 0.0220593 * (x - 5.8123))" /> 
				<E VAR="gamma" DOMAIN="2"  VALUE="0.277464 * (1 + 0.0327496 * (x - 5.8123))" /> 
				<E VAR="gamma" DOMAIN="3"  VALUE="0.542964 * (1 + 0.0680873 * (x - 9.72058))" /> 
				<E VAR="gamma" DOMAIN="4"  VALUE="3.43812 * (1 + 0.0550745 * (x - 9.72058))" /> 
				<E VAR="gamma" DOMAIN="5"  VALUE="16.2991 * (1 + 0.0198237 * (x - 13.6289))" /> 
				<E VAR="gamma" DOMAIN="6"  VALUE="2.13407 * (1 + 0.0112898 * (x - 13.6289))" /> 
				<E VAR="gamma" DOMAIN="7"  VALUE="16.2991 * (1 + 0.00860542 * (x - 62.2317))" /> 
				<E VAR="gamma" DOMAIN="8"  VALUE="16.2991 * (1 + 0.0154859 * (x - 62.2317))" /> 
				<E VAR="gamma" DOMAIN="9"  VALUE="37.1709 * (1 + 0.0209443 * (x - 69.9481))" /> 
				<E VAR="gamma" DOMAIN="10"  VALUE="20.297 * (1 + 0.00900352 * (x - 69.9481))" /> 
				<E VAR="gamma" DOMAIN="11"  VALUE="8.49 * (1 + 0.0169425 * (x - 20.5435))" /> 
				<E VAR="gamma" DOMAIN="12"  VALUE="29.096 * (1 + 0.0268663 * (x - 20.5435))" /> 
				<E VAR="gamma" DOMAIN="13"  VALUE="0.129883 * (1 + 0.00709805 * (x - 8.11718))" /> 
				<E VAR="gamma" DOMAIN="14"  VALUE="4.01789 * (1 + 0.0390343 * (x - 8.11718))" /> 
				<E VAR="gamma" DOMAIN="15"  VALUE="12.9781 * (1 + 0.0155628 * (x - 24.1511))" /> 
				<E VAR="gamma" DOMAIN="16"  VALUE="42.1917 * (1 + 0.0236506 * (x - 24.1511))" /> 
				<E VAR="gamma" DOMAIN="17"  VALUE="0.140312 * (1 + 0.0103406 * (x - 12.6267))" /> 
				<E VAR="gamma" DOMAIN="18"  VALUE="0.57302 * (1 + 0.0747501 * (x - 12.6267))" /> 
				<E VAR="gamma" DOMAIN="19"  VALUE="16.2991 * (1 + 0.0199403 * (x - 16.535))" /> 
				<E VAR="gamma" DOMAIN="20"  VALUE="2.13407 * (1 + 0.0112898 * (x - 16.535))" /> 
				<E VAR="gamma" DOMAIN="21"  VALUE="17.7473 * (1 + 0.0103867 * (x - 65.1379))" /> 
				<E VAR="gamma" DOMAIN="22"  VALUE="12.9781 * (1 + 0 * (x - 65.1379))" /> 
				<E VAR="gamma" DOMAIN="23"  VALUE="45.9466 * (1 + 0 * (x - 72.8542))" /> 
				<E VAR="gamma" DOMAIN="24"  VALUE="13.9686 * (1 + 0.00724264 * (x - 72.8542))" /> 
				<E VAR="gamma" DOMAIN="25"  VALUE="0.241178 * (1 + 0.03257 * (x - 18.6395))" /> 
				<E VAR="gamma" DOMAIN="26"  VALUE="0.17559 * (1 + 0.0209263 * (x - 18.6395))" /> 
				<E VAR="gamma" DOMAIN="27"  VALUE="0.250492 * (1 + 0 * (x - 30.6649))" /> 
				<E VAR="gamma" DOMAIN="28"  VALUE="0.449773 * (1 + 0.0693381 * (x - 30.6649))" /> 
				<E VAR="gamma" DOMAIN="29"  VALUE="0.812982 * (1 + 0.0373614 * (x - 32.9698))" /> 
				<E VAR="gamma" DOMAIN="30"  VALUE="3.83641 * (1 + 0.0349441 * (x - 32.9698))" /> 
				<E VAR="gamma" DOMAIN="31"  VALUE="20.297 * (1 + 0.0107693 * (x - 35.2747))" /> 
				<E VAR="gamma" DOMAIN="32"  VALUE="13.482 * (1 + 0.0142957 * (x - 35.2747))" /> 
				<E VAR="gamma" DOMAIN="33"  VALUE="0.884221 * (1 + 0.0203868 * (x - 36.7779))" /> 
				<E VAR="gamma" DOMAIN="34"  VALUE="0.271482 * (1 + 0.00909905 * (x - 36.7779))" /> 
				<E VAR="gamma" DOMAIN="35"  VALUE="4.06491 * (1 + 0 * (x - 39.0827))" /> 
				<E VAR="gamma" DOMAIN="36"  VALUE="0.263207 * (1 + 0 * (x - 39.0827))" /> 
				<E VAR="gamma" DOMAIN="37"  VALUE="4.06491 * (1 + 0 * (x - 41.3876))" /> 
				<E VAR="gamma" DOMAIN="38"  VALUE="0.268666 * (1 + 0.00509425 * (x - 41.3876))" /> 
				<E VAR="gamma" DOMAIN="39"  VALUE="4.72891 * (1 + 0.0762782 * (x - 53.6135))" /> 
				<E VAR="gamma" DOMAIN="40"  VALUE="0.293004 * (1 + 0.0196866 * (x - 53.6135))" /> 
				<E VAR="gamma" DOMAIN="41"  VALUE="1.19777 * (1 + 0.0241145 * (x - 55.9184))" /> 
				<E VAR="gamma" DOMAIN="42"  VALUE="1.19777 * (1 + 0.0241145 * (x - 55.9184))" /> 
				<E VAR="gamma" DOMAIN="43"  VALUE="4.09187 * (1 + 0.0042143 * (x - 62.7328))" /> 
				<E VAR="gamma" DOMAIN="44"  VALUE="19.9351 * (1 + 0 * (x - 62.7328))" /> 
				<E VAR="gamma" DOMAIN="45"  VALUE="13.4617 * (1 + 0.00735294 * (x - 79.368))" /> 
				<E VAR="gamma" DOMAIN="46"  VALUE="19.9351 * (1 + 0.0075149 * (x - 79.368))" /> 
				<E VAR="gamma" DOMAIN="47"  VALUE="28.9603 * (1 + 0.00365151 * (x - 130.376))" /> 
				<E VAR="gamma" DOMAIN="48"  VALUE="37.0236 * (1 + 0.00389349 * (x - 130.376))" /> 
				<E VAR="gamma" DOMAIN="49"  VALUE="4.09187 * (1 + 0.0042143 * (x - 62.7328))" /> 
				<E VAR="gamma" DOMAIN="50"  VALUE="19.9351 * (1 + 0 * (x - 62.7328))" /> 
				<E VAR="gamma" DOMAIN="51"  VALUE="13.4617 * (1 + 0.00735294 * (x - 79.368))" /> 
				<E VAR="gamma" DOMAIN="52"  VALUE="19.9351 * (1 + 0.0075149 * (x - 79.368))" /> 
				<E VAR="gamma" DOMAIN="53"  VALUE="28.9603 * (1 + 0.00365151 * (x - 130.376))" /> 
				<E VAR="gamma" DOMAIN="54"  VALUE="37.0236 * (1 + 0.00389349 * (x - 130.376))" /> 
		</FUNCTION> 

		<FUNCTION NAME="StrainStiffening"> 
				<E VAR="alpha" DOMAIN="0"  VALUE="0.624098 * (1 + 9.1339e-05 * (x - 0))" /> 
				<E VAR="alpha" DOMAIN="1"  VALUE="0.64156 * (1 + 0.00351235 * (x - 5.8123))" /> 
				<E VAR="alpha" DOMAIN="2"  VALUE="0.669823 * (1 + 0.00674351 * (x - 5.8123))" /> 
				<E VAR="alpha" DOMAIN="3"  VALUE="0.781057 * (1 + 0.0210897 * (x - 9.72058))" /> 
				<E VAR="alpha" DOMAIN="4"  VALUE="0.792431 * (1 + 0.0221055 * (x - 9.72058))" /> 
				<E VAR="alpha" DOMAIN="5"  VALUE="1.32017 * (1 + 0.00951221 * (x - 13.6289))" /> 
				<E VAR="alpha" DOMAIN="6"  VALUE="0.887708 * (1 + 0.00470282 * (x - 13.6289))" /> 
				<E VAR="alpha" DOMAIN="7"  VALUE="1.32017 * (1 + 0.00387761 * (x - 62.2317))" /> 
				<E VAR="alpha" DOMAIN="8"  VALUE="1.32017 * (1 + 0.00657153 * (x - 62.2317))" /> 
				<E VAR="alpha" DOMAIN="9"  VALUE="1.92836 * (1 + 0.0119266 * (x - 69.9481))" /> 
				<E VAR="alpha" DOMAIN="10"  VALUE="1.44601 * (1 + 0.00421542 * (x - 69.9481))" /> 
				<E VAR="alpha" DOMAIN="11"  VALUE="1.04076 * (1 + 0.00681841 * (x - 20.5435))" /> 
				<E VAR="alpha" DOMAIN="12"  VALUE="1.70432 * (1 + 0.0168929 * (x - 20.5435))" /> 
				<E VAR="alpha" DOMAIN="13"  VALUE="0.661868 * (1 + 0.00128771 * (x - 8.11718))" /> 
				<E VAR="alpha" DOMAIN="14"  VALUE="0.82733 * (1 + 0.0166347 * (x - 8.11718))" /> 
				<E VAR="alpha" DOMAIN="15"  VALUE="1.20874 * (1 + 0.00689998 * (x - 24.1511))" /> 
				<E VAR="alpha" DOMAIN="16"  VALUE="2.06381 * (1 + 0.0157946 * (x - 24.1511))" /> 
				<E VAR="alpha" DOMAIN="17"  VALUE="0.671239 * (1 + 0.002033 * (x - 12.6267))" /> 
				<E VAR="alpha" DOMAIN="18"  VALUE="0.792431 * (1 + 0.0238434 * (x - 12.6267))" /> 
				<E VAR="alpha" DOMAIN="19"  VALUE="1.32017 * (1 + 0.00956817 * (x - 16.535))" /> 
				<E VAR="alpha" DOMAIN="20"  VALUE="0.887708 * (1 + 0.00470282 * (x - 16.535))" /> 
				<E VAR="alpha" DOMAIN="21"  VALUE="1.36661 * (1 + 0.00493612 * (x - 65.1379))" /> 
				<E VAR="alpha" DOMAIN="22"  VALUE="1.20874 * (1 + 0 * (x - 65.1379))" /> 
				<E VAR="alpha" DOMAIN="23"  VALUE="2.16369 * (1 + 0 * (x - 72.8542))" /> 
				<E VAR="alpha" DOMAIN="24"  VALUE="1.24281 * (1 + 0.00296803 * (x - 72.8542))" /> 
				<E VAR="alpha" DOMAIN="25"  VALUE="0.757327 * (1 + 0.00998981 * (x - 18.6395))" /> 
				<E VAR="alpha" DOMAIN="26"  VALUE="0.702423 * (1 + 0.00548887 * (x - 18.6395))" /> 
				<E VAR="alpha" DOMAIN="27"  VALUE="0.764734 * (1 + 0 * (x - 30.6649))" /> 
				<E VAR="alpha" DOMAIN="28"  VALUE="0.901749 * (1 + 0.022569 * (x - 30.6649))" /> 
				<E VAR="alpha" DOMAIN="29"  VALUE="1.09099 * (1 + 0.0134395 * (x - 32.9698))" /> 
				<E VAR="alpha" DOMAIN="30"  VALUE="1.06957 * (1 + 0.0136459 * (x - 32.9698))" /> 
				<E VAR="alpha" DOMAIN="31"  VALUE="1.44601 * (1 + 0.00482331 * (x - 35.2747))" /> 
				<E VAR="alpha" DOMAIN="32"  VALUE="1.22617 * (1 + 0.00568029 * (x - 35.2747))" /> 
				<E VAR="alpha" DOMAIN="33"  VALUE="0.897103 * (1 + 0.00654137 * (x - 36.7779))" /> 
				<E VAR="alpha" DOMAIN="34"  VALUE="0.781057 * (1 + 0.00244816 * (x - 36.7779))" /> 
				<E VAR="alpha" DOMAIN="35"  VALUE="1.09099 * (1 + 0 * (x - 39.0827))" /> 
				<E VAR="alpha" DOMAIN="36"  VALUE="0.774683 * (1 + 0 * (x - 39.0827))" /> 
				<E VAR="alpha" DOMAIN="37"  VALUE="1.09099 * (1 + 0 * (x - 41.3876))" /> 
				<E VAR="alpha" DOMAIN="38"  VALUE="0.778896 * (1 + 0.00139708 * (x - 41.3876))" /> 
				<E VAR="alpha" DOMAIN="39"  VALUE="1.15073 * (1 + 0.0353982 * (x - 53.6135))" /> 
				<E VAR="alpha" DOMAIN="40"  VALUE="0.797268 * (1 + 0.00548919 * (x - 53.6135))" /> 
				<E VAR="alpha" DOMAIN="41"  VALUE="0.985605 * (1 + 0.00837133 * (x - 55.9184))" /> 
				<E VAR="alpha" DOMAIN="42"  VALUE="0.985605 * (1 + 0.00837133 * (x - 55.9184))" /> 
				<E VAR="alpha" DOMAIN="43"  VALUE="1.09348 * (1 + 0.00150671 * (x - 62.7328))" /> 
				<E VAR="alpha" DOMAIN="44"  VALUE="1.4349 * (1 + 0 * (x - 62.7328))" /> 
				<E VAR="alpha" DOMAIN="45"  VALUE="1.22548 * (1 + 0.0034134 * (x - 79.368))" /> 
				<E VAR="alpha" DOMAIN="46"  VALUE="1.4349 * (1 + 0.00338013 * (x - 79.368))" /> 
				<E VAR="alpha" DOMAIN="47"  VALUE="1.70047 * (1 + 0.00187433 * (x - 130.376))" /> 
				<E VAR="alpha" DOMAIN="48"  VALUE="1.92435 * (1 + 0.00217911 * (x - 130.376))" /> 
				<E VAR="alpha" DOMAIN="49"  VALUE="1.09348 * (1 + 0.00150671 * (x - 62.7328))" /> 
				<E VAR="alpha" DOMAIN="50"  VALUE="1.4349 * (1 + 0 * (x - 62.7328))" /> 
				<E VAR="alpha" DOMAIN="51"  VALUE="1.22548 * (1 + 0.0034134 * (x - 79.368))" /> 
				<E VAR="alpha" DOMAIN="52"  VALUE="1.4349 * (1 + 0.00338013 * (x - 79.368))" /> 
				<E VAR="alpha" DOMAIN="53"  VALUE="1.70047 * (1 + 0.00187433 * (x - 130.376))" /> 
				<E VAR="alpha" DOMAIN="54"  VALUE="1.92435 * (1 + 0.00217911 * (x - 130.376))" /> 
		</FUNCTION> 

</CONDITIONS> 

</NEKTAR>